pypi_search_sample/__init__.py
pypi_search_sample-0.1.dist-info/DESCRIPTION.rst
pypi_search_sample-0.1.dist-info/METADATA
pypi_search_sample-0.1.dist-info/RECORD
pypi_search_sample-0.1.dist-info/WHEEL
pypi_search_sample-0.1.dist-info/metadata.json
pypi_search_sample-0.1.dist-info/top_level.txt
