Metadata-Version: 2.0
Name: pypi-search-sample
Version: 0.1
Summary: Sample package for the infamous pypi-search package on PyPI
Home-page: UNKNOWN
Author: John Yeuk Hon Wong
Author-email: yeukhon@acm.org
License: UNKNOWN
Keywords: pypi-search,pypi-search-sample
Platform: UNKNOWN
Classifier: Development Status :: 3 - Alpha
Classifier: Intended Audience :: Developers
Classifier: Programming Language :: Python :: 2
Classifier: Programming Language :: Python :: 2.7
Classifier: Programming Language :: Python :: 3
Classifier: Programming Language :: Python :: 3.2
Classifier: Programming Language :: Python :: 3.3
Classifier: Programming Language :: Python :: 3.4
Classifier: Programming Language :: Python :: 3.5
